imgbox/__init__.py
imgbox/imgbox.py
imgbox/font/600.ttf
imgbox-1.0.8.dist-info/METADATA
imgbox-1.0.8.dist-info/WHEEL
imgbox-1.0.8.dist-info/top_level.txt
imgbox-1.0.8.dist-info/RECORD
