Metadata-Version: 2.1
Name: imgbox
Version: 1.0.8
Summary: 用 pillow 画目标检测的框，支持中文（自带字体）
Home-page: https://github.com/aier-art/imgbox
Author: xxai.art
Author-email: xxai.art@gmail.com
Requires-Dist: pillow
